[
    {
        "id": 1388534400000,
        "author": "Bunchhieng Soth",
        "text": "Hey There!"
    },
    {
        "id": 1457159949394,
        "author": "Bunchhieng",
        "text": "Soth"
    },
    {
        "id": 1457159955257,
        "author": "Kaka",
        "text": "jojo"
    },
    {
        "id": 1457160161743,
        "author": "Bunchhieng",
        "text": "Sot"
    },
    {
        "id": 1457160167923,
        "author": "Cambodia",
        "text": "yoo"
    },
    {
        "id": 1457160237759,
        "author": "fdsa",
        "text": "sdf"
    },
    {
        "id": 1457160311779,
        "author": "dsaf",
        "text": "dsf"
    },
    {
        "id": 1457160503623,
        "author": "I love you",
        "text": "Bunchhieng"
    }
]